odoo/addons/mis_builder_analytic/README.rst
odoo/addons/mis_builder_analytic/__init__.py
odoo/addons/mis_builder_analytic/__manifest__.py
odoo/addons/mis_builder_analytic/i18n/it.po
odoo/addons/mis_builder_analytic/i18n/mis_builder_analytic.pot
odoo/addons/mis_builder_analytic/models/__init__.py
odoo/addons/mis_builder_analytic/models/mis_account_analytic_line.py
odoo/addons/mis_builder_analytic/readme/CONTRIBUTORS.md
odoo/addons/mis_builder_analytic/readme/DESCRIPTION.md
odoo/addons/mis_builder_analytic/readme/USAGE.md
odoo/addons/mis_builder_analytic/security/ir.model.access.csv
odoo/addons/mis_builder_analytic/static/description/icon.png
odoo/addons/mis_builder_analytic/static/description/index.html
odoo/addons/mis_builder_analytic/views/mis_account_analytic_line_views.xml
odoo_addon_mis_builder_analytic-17.0.1.0.0.3.dist-info/METADATA
odoo_addon_mis_builder_analytic-17.0.1.0.0.3.dist-info/WHEEL
odoo_addon_mis_builder_analytic-17.0.1.0.0.3.dist-info/top_level.txt
odoo_addon_mis_builder_analytic-17.0.1.0.0.3.dist-info/RECORD
